django_sites_extensions/__init__.py
django_sites_extensions/apps.py
django_sites_extensions/middleware.py
django_sites_extensions/models.py
django_sites_extensions/signals.py
edx_django_sites_extensions-5.1.0.dist-info/AUTHORS
edx_django_sites_extensions-5.1.0.dist-info/LICENSE.txt
edx_django_sites_extensions-5.1.0.dist-info/METADATA
edx_django_sites_extensions-5.1.0.dist-info/WHEEL
edx_django_sites_extensions-5.1.0.dist-info/top_level.txt
edx_django_sites_extensions-5.1.0.dist-info/RECORD
