Metadata-Version: 2.1
Name: edx-django-sites-extensions
Version: 5.1.0
Summary: Custom extensions for the Django sites framework
Home-page: https://github.com/openedx/edx-django-sites-extensions
Author: edX
Author-email: oscm@edx.org
License: AGPL
Keywords: Django sites edx
Classifier: Development Status :: 4 - Beta
Classifier: License :: OSI Approved :: GNU Affero General Public License v3
Classifier: Programming Language :: Python
Classifier: Programming Language :: Python :: 3.11
Classifier: Programming Language :: Python :: 3.12
Classifier: Topic :: Internet
Classifier: Intended Audience :: Developers
Classifier: Environment :: Web Environment
Classifier: Framework :: Django
Classifier: Framework :: Django :: 4.2
Classifier: Framework :: Django :: 5.2
License-File: LICENSE.txt
License-File: AUTHORS
Requires-Dist: Django
